{
	"f_fields":
	{
		"classpath":"field",
		"data":
		[
			{
				"f_inputtype":0,
				"f_datatype_db":2,
				"f_order":1,
				"f_allowblank":false,
				"f_length":10,
				"f_datatype_java":2,
				"f_width":0,
				"f_height":0,
				"f_top":0,
				"f_left":0,
				"f_name":"ID",
				"f_caption":"ID",
				"f_key":"ID",
				"f_class":"field",
				"f_i_parent":
				{
					"classpath":"table",
					"data":"mkScore.T_MK_BPC_SCORE_DAY"
				}
			},
			{
				"f_inputtype":0,
				"f_datatype_db":2,
				"f_order":2,
				"f_allowblank":true,
				"f_length":10,
				"f_datatype_java":2,
				"f_width":0,
				"f_height":0,
				"f_top":0,
				"f_left":0,
				"f_name":"F_USER_ID",
				"f_caption":"F_USER_ID",
				"f_key":"F_USER_ID",
				"f_class":"field",
				"f_i_parent":
				{
					"classpath":"table",
					"data":"mkScore.T_MK_BPC_SCORE_DAY"
				}
			},
			{
				"f_inputtype":0,
				"f_datatype_db":4,
				"f_order":3,
				"f_allowblank":true,
				"f_length":0,
				"f_datatype_java":4,
				"f_width":0,
				"f_height":0,
				"f_top":0,
				"f_left":0,
				"f_name":"F_SCOREDATE",
				"f_caption":"F_SCOREDATE",
				"f_key":"F_SCOREDATE",
				"f_class":"field",
				"f_i_parent":
				{
					"classpath":"table",
					"data":"mkScore.T_MK_BPC_SCORE_DAY"
				}
			},
			{
				"f_inputtype":4,
				"f_datatype_db":5,
				"f_order":4,
				"f_allowblank":true,
				"f_length":10,
				"f_datatype_java":5,
				"f_width":0,
				"f_height":0,
				"f_top":0,
				"f_left":0,
				"f_name":"F_SCORE",
				"f_caption":"F_SCORE",
				"f_key":"F_SCORE",
				"f_class":"field",
				"f_i_parent":
				{
					"classpath":"table",
					"data":"mkScore.T_MK_BPC_SCORE_DAY"
				}
			},
			{
				"f_inputtype":0,
				"f_datatype_db":2,
				"f_order":5,
				"f_allowblank":true,
				"f_length":10,
				"f_datatype_java":2,
				"f_width":0,
				"f_height":0,
				"f_top":0,
				"f_left":0,
				"f_name":"F_MANAGER_ID",
				"f_caption":"F_MANAGER_ID",
				"f_key":"F_MANAGER_ID",
				"f_class":"field",
				"f_i_parent":
				{
					"classpath":"table",
					"data":"mkScore.T_MK_BPC_SCORE_DAY"
				}
			},
			{
				"f_inputtype":0,
				"f_datatype_db":1,
				"f_order":6,
				"f_allowblank":true,
				"f_length":50,
				"f_datatype_java":1,
				"f_width":0,
				"f_height":0,
				"f_top":0,
				"f_left":0,
				"f_name":"F_UPDATOR_NAME",
				"f_caption":"F_UPDATOR_NAME",
				"f_key":"F_UPDATOR_NAME",
				"f_class":"field",
				"f_i_parent":
				{
					"classpath":"table",
					"data":"mkScore.T_MK_BPC_SCORE_DAY"
				}
			},
			{
				"f_inputtype":0,
				"f_datatype_db":4,
				"f_order":7,
				"f_allowblank":true,
				"f_length":0,
				"f_datatype_java":4,
				"f_width":0,
				"f_height":0,
				"f_top":0,
				"f_left":0,
				"f_name":"F_UPDATE_TIME",
				"f_caption":"F_UPDATE_TIME",
				"f_key":"F_UPDATE_TIME",
				"f_class":"field",
				"f_i_parent":
				{
					"classpath":"table",
					"data":"mkScore.T_MK_BPC_SCORE_DAY"
				}
			}
		]
	},
	"f_keyfield":"ID",
	"f_forms":
	{
		"classpath":"tableform",
		"data":
		[
			{
				"f_width":0,
				"f_height":0,
				"f_columns":1,
				"f_fieldmap":
				{
					"ID":
					{
						"mode":"1000"
					},
					"F_USER_ID":
					{
						"mode":"0010"
					},
					"F_SCOREDATE":
					{
						"mode":"0010"
					},
					"F_SCORE":
					{
						"mode":"0010"
					},
					"F_MANAGER_ID":
					{
						"mode":"0010"
					},
					"F_UPDATOR_NAME":
					{
						"mode":"0010"
					},
					"F_UPDATE_TIME":
					{
						"mode":"0010"
					}
				},
				"f_name":"frmDailyScore",
				"f_caption":"frmDailyScore",
				"f_key":"frmDailyScore",
				"f_class":"tableform",
				"f_i_parent":
				{
					"classpath":"table",
					"data":"mkScore.T_MK_BPC_SCORE_DAY"
				}
			}
		]
	},
	"f_name":"T_MK_BPC_SCORE_DAY",
	"f_caption":"T_MK_BPC_SCORE_DAY",
	"f_key":"T_MK_BPC_SCORE_DAY",
	"f_class":"table",
	"f_i_parent":
	{
		"classpath":"module",
		"data":"mkScore"
	}
}