{
	"f_where":"F_USER_ID = |userid|  AND F_STATE<>'关闭' and F_STATE <>'挂起'  AND  F_PLAN_START_TIME <= to_date('|date|','yyyy-mm-dd') ",
	"f_from":"V_MK_BPC_TASK_WORK",
	"f_views":
	{
		"classpath":"view",
		"data":
		[
			{
				"f_url":"framework/engine/view/view.worklog",
				"f_columns":
				{
					"classpath":"column",
					"data":
					[
						{
							"f_type":0,
							"f_order":1,
							"f_query_type":0,
							"f_orderable":false,
							"f_name":"ID",
							"f_caption":"ID",
							"f_key":"ID",
							"f_class":"column",
							"f_i_parent":
							{
								"classpath":"view",
								"data":"mkTest.qTaskWork.vTaskWork"
							}
						},
						{
							"f_type":1,
							"f_order":2,
							"f_query_type":1,
							"f_orderable":false,
							"f_name":"F_TITLE",
							"f_caption":"标题",
							"f_key":"F_TITLE",
							"f_class":"column",
							"f_i_parent":
							{
								"classpath":"view",
								"data":"mkTest.qTaskWork.vTaskWork"
							}
						}
					]
				},
				"f_keycolumn":"ID",
				"f_single_select":true,
				"f_page_size":0,
				"f_isquery":false,
				"f_issummary":false,
				"f_autoexpandcolumn":"F_TITLE",
				"f_enable_favorite":false,
				"f_name":"vTaskWork",
				"f_caption":"任务日志列表",
				"f_key":"vTaskWork",
				"f_config":
				{
					"editorform":"mkAddressBook.T_MK_SYS_DICTIONARY_DATA.frmNotifyTag"
				},
				"f_class":"view",
				"f_i_parent":
				{
					"classpath":"query",
					"data":"mkTest.qTaskWork"
				}
			}
		]
	},
	"f_orderby":"",
	"f_name":"qTaskWork",
	"f_caption":"qTaskWork",
	"f_key":"qTaskWork",
	"f_class":"query",
	"f_i_parent":
	{
		"classpath":"module",
		"data":"mkTest"
	}
}